psaiops/__init__.py
psaiops/combine/__init__.py
psaiops/combine/app.py
psaiops/common/__init__.py
psaiops/common/data.py
psaiops/common/model.py
psaiops/common/style.py
psaiops/common/tokenizer.py
psaiops/compose/__init__.py
psaiops/compose/contrast/__init__.py
psaiops/compose/contrast/app.py
psaiops/compose/contrast/lib.py
psaiops/compose/maths/__init__.py
psaiops/compose/maths/app.py
psaiops/compose/maths/lib.py
psaiops/edit/__init__.py
psaiops/reverse/__init__.py
psaiops/score/__init__.py
psaiops/score/attention/__init__.py
psaiops/score/attention/app.py
psaiops/score/attention/lib.py
psaiops/score/residual/__init__.py
psaiops/score/residual/app.py
psaiops/score/residual/lib.py
psaiops/score/router/__init__.py
psaiops/score/router/app.py
psaiops/score/router/lib.py
psaiops/score/shapley/__init__.py
psaiops/score/shapley/app.py
psaiops/score/shapley/lib.py
psaiops/score/similarity/__init__.py
psaiops/score/similarity/app.py
psaiops/score/similarity/lib.py
psaiops/score/surprisal/__init__.py
psaiops/score/surprisal/app.py
psaiops/score/surprisal/lib.py
psaiops-0.6.7.dist-info/METADATA
psaiops-0.6.7.dist-info/WHEEL
psaiops-0.6.7.dist-info/licenses/.github/LICENSE.md
psaiops-0.6.7.dist-info/RECORD
