Metadata-Version: 2.4
Name: psaiops
Version: 0.6.7
Summary: Web apps to inspect & engineer NN activations.
Author-email: apehex <17317183+apehex@users.noreply.github.com>
License-Expression: AGPL-3.0
License-File: .github/LICENSE.md
Requires-Python: <3.14,>=3.10
Requires-Dist: accelerate>=1.10
Requires-Dist: deformers>=0.0
Requires-Dist: gradio>=5.0
Requires-Dist: kernels>=0.10
Requires-Dist: matplotlib>=3.10
Requires-Dist: mlable-torch>=0.2
Requires-Dist: requests>=2.0
Requires-Dist: triton==3.4
